cherrypy_utils/__about__.py
cherrypy_utils/__init__.py
cherrypy_utils/application_data.py
cherrypy_utils/authentication.py
cherrypy_utils/cherrypy_sqlalchemy_utils.py
cherrypy_utils/database.py
cherrypy_utils/database_model.py
cherrypy_utils/docker_utils.py
cherrypy_utils/json_utils.py
cherrypy_utils/reactjs_utils.py
cherrypy_utils/templating.py
cherrypy_utils/timestamp_utils.py
cherrypy_utils/url_utils.py
cherrypy_utils/login/__init__.py
cherrypy_utils/login/ldap_auth.py
cherrypy_utils/login/models.py
cherrypy_utils-1.4.0.dist-info/METADATA
cherrypy_utils-1.4.0.dist-info/WHEEL
cherrypy_utils-1.4.0.dist-info/RECORD
