Metadata-Version: 2.3
Name: cherrypy_utils
Version: 1.4.0
Summary: Collection of utility functions and modules for cherrypy web servers
Project-URL: Homepage, https://mindmodeling.afresearchlab.dev/
Project-URL: Bug Tracker, https://mindmodeling.afresearchlab.dev/
Author-email: Ian Davis <ian.davis.18.ctr@afrl.af.mil>
Classifier: Operating System :: OS Independent
Classifier: Programming Language :: Python :: 3
Requires-Python: >=3.6
Requires-Dist: cherrypy
Requires-Dist: jinja2
Requires-Dist: python-dateutil
Requires-Dist: pytz
Requires-Dist: requests
Requires-Dist: sqlalchemy
Provides-Extra: optionals
